ec2_restore/__init__.py
ec2_restore/modules/__init__.py
ec2_restore/modules/aws_client.py
ec2_restore/modules/cli.py
ec2_restore/modules/display.py
ec2_restore/modules/restore_manager.py
ec2_restore/modules/ssm_manager.py
ec2_restore-1.1.0.data/data/ec2_restore/config/config.yaml.example
ec2_restore-1.1.0.dist-info/licenses/LICENSE
ec2_restore-1.1.0.dist-info/METADATA
ec2_restore-1.1.0.dist-info/WHEEL
ec2_restore-1.1.0.dist-info/entry_points.txt
ec2_restore-1.1.0.dist-info/top_level.txt
ec2_restore-1.1.0.dist-info/RECORD
