Metadata-Version: 2.4
Name: ec2-restore
Version: 1.1.0
Summary: A tool for restoring EC2 instances from AMIs
Home-page: https://github.com/jyothishkshatri/ec2-restore
Author: Jyothish Kshatri
Author-email: kshatri.jyothish3@gmail.com
Classifier: Programming Language :: Python :: 3
Classifier: License :: OSI Approved :: MIT License
Classifier: Operating System :: OS Independent
Requires-Python: >=3.8
License-File: LICENSE
Requires-Dist: click>=8.0.0
Requires-Dist: boto3>=1.26.0
Requires-Dist: rich>=10.0.0
Requires-Dist: pyyaml>=6.0.0
Dynamic: author
Dynamic: author-email
Dynamic: classifier
Dynamic: description
Dynamic: description-content-type
Dynamic: home-page
Dynamic: license-file
Dynamic: requires-dist
Dynamic: requires-python
Dynamic: summary
